arrow_odbc/__init__.py
arrow_odbc/buffer.py
arrow_odbc/connect.py
arrow_odbc/connection_raii.py
arrow_odbc/error.py
arrow_odbc/insert_into_table.py
arrow_odbc/log.py
arrow_odbc/pool.py
arrow_odbc/read_arrow_batches_from_odbc.py
arrow_odbc/reader.py
arrow_odbc/writer.py
arrow_odbc/arrow_odbc/__init__.py
arrow_odbc/arrow_odbc/ffi.py
arrow_odbc/arrow_odbc/libarrow_odbc.so
arrow_odbc-9.3.3.dist-info/METADATA
arrow_odbc-9.3.3.dist-info/WHEEL
arrow_odbc-9.3.3.dist-info/RECORD
arrow_odbc-9.3.3.dist-info/licenses/LICENSE
