Metadata-Version: 2.4
Name: arrow-odbc
Version: 9.3.3
Requires-Dist: cffi
Requires-Dist: pyarrow>=8.0.0
License-File: LICENSE
Summary: Read the data of an ODBC data source as sequence of Apache Arrow record batches.
Author: Markus Klein
License-Expression: MIT
Requires-Python: >=3.10
Project-URL: repository, https://github.com/pacman82/arrow-odbc-py
Project-URL: changelog, https://github.com/pacman82/arrow-odbc-py/blob/main/CHANGELOG.md
